expertai/extract/__init__.py
expertai/extract/authentication.py
expertai/extract/extract_client.py
expertai/extract/openapi/__init__.py
expertai/extract/openapi/client/__init__.py
expertai/extract/openapi/client/api_client.py
expertai/extract/openapi/client/configuration.py
expertai/extract/openapi/client/exceptions.py
expertai/extract/openapi/client/model_utils.py
expertai/extract/openapi/client/rest.py
expertai/extract/openapi/client/api/__init__.py
expertai/extract/openapi/client/api/default_api.py
expertai/extract/openapi/client/apis/__init__.py
expertai/extract/openapi/client/model/__init__.py
expertai/extract/openapi/client/model/layout_document_async_response.py
expertai/extract/openapi/client/model/layout_item.py
expertai/extract/openapi/client/model/layout_request.py
expertai/extract/openapi/client/model/recognition_task_output.py
expertai/extract/openapi/client/models/__init__.py
expertai/extract/openapi/client/test/__init__.py
expertai/extract/openapi/client/test/test_default_api.py
expertai/extract/openapi/client/test/test_layout_document_async_response.py
expertai/extract/openapi/client/test/test_layout_item.py
expertai/extract/openapi/client/test/test_layout_request.py
expertai/extract/openapi/client/test/test_recognition_task_output.py
expertai_extract-0.1.2.dist-info/LICENSE
expertai_extract-0.1.2.dist-info/METADATA
expertai_extract-0.1.2.dist-info/WHEEL
expertai_extract-0.1.2.dist-info/top_level.txt
expertai_extract-0.1.2.dist-info/RECORD
